candig_schemas-1.1.0-py3.6-nspkg.pth
candig/schemas/__init__.py
candig/schemas/_protocol_version.py
candig/schemas/_version.py
candig/schemas/pb.py
candig/schemas/protocol.py
candig/schemas/candig/__init__.py
candig/schemas/candig/allele_annotation_service_pb2.py
candig/schemas/candig/allele_annotations_pb2.py
candig/schemas/candig/bio_metadata_pb2.py
candig/schemas/candig/bio_metadata_service_pb2.py
candig/schemas/candig/clinical_metadata_pb2.py
candig/schemas/candig/clinical_metadata_service_pb2.py
candig/schemas/candig/common_pb2.py
candig/schemas/candig/genotype_phenotype_pb2.py
candig/schemas/candig/genotype_phenotype_service_pb2.py
candig/schemas/candig/genotype_service_pb2.py
candig/schemas/candig/metadata_pb2.py
candig/schemas/candig/metadata_service_pb2.py
candig/schemas/candig/peer_service_pb2.py
candig/schemas/candig/pipeline_metadata_pb2.py
candig/schemas/candig/pipeline_metadata_service_pb2.py
candig/schemas/candig/read_service_pb2.py
candig/schemas/candig/reads_pb2.py
candig/schemas/candig/reference_service_pb2.py
candig/schemas/candig/references_pb2.py
candig/schemas/candig/rna_quantification_pb2.py
candig/schemas/candig/rna_quantification_service_pb2.py
candig/schemas/candig/search_service_pb2.py
candig/schemas/candig/sequence_annotation_service_pb2.py
candig/schemas/candig/sequence_annotations_pb2.py
candig/schemas/candig/variant_service_pb2.py
candig/schemas/candig/variants_pb2.py
candig/schemas/google/__init__.py
candig/schemas/google/api/__init__.py
candig/schemas/google/api/annotations_pb2.py
candig/schemas/google/api/http_pb2.py
candig/schemas/hacks/__init__.py
candig/schemas/hacks/googhack.py
candig_schemas-1.1.0.dist-info/LICENSE
candig_schemas-1.1.0.dist-info/METADATA
candig_schemas-1.1.0.dist-info/WHEEL
candig_schemas-1.1.0.dist-info/namespace_packages.txt
candig_schemas-1.1.0.dist-info/top_level.txt
candig_schemas-1.1.0.dist-info/zip-safe
candig_schemas-1.1.0.dist-info/RECORD
