Metadata-Version: 2.1
Name: candig-schemas
Version: 1.1.0
Summary: CanDIG API Schemas
Home-page: https://github.com/candig/candig-schemas
Author: CanDIG Team
Author-email: info@distributedgenomics.ca
License: Apache License 2.0
Keywords: genomics,candig
Platform: UNKNOWN
Classifier: Intended Audience :: Science/Research
Classifier: License :: OSI Approved :: Apache Software License
Classifier: Natural Language :: English
Classifier: Programming Language :: Python :: 3.6
Classifier: Topic :: Scientific/Engineering :: Bio-Informatics
Requires-Dist: protobuf (==3.3.0)
